{
  "_meta": {
    "sources": [
      "../common/models",
      "./models"
    ]
  },
  "User": {
    "dataSource": "sbvrdev",
    "public": false
  },
  "AccessToken": {
    "dataSource": "sbvrdev",
    "public": false
  },
  "ACL": {
    "dataSource": "sbvrdev",
    "public": false
  },
  "RoleMapping": {
    "dataSource": "sbvrdev",
    "public": false
  },
  "Role": {
    "dataSource": "sbvrdev",
    "public": false
  },
  "account": {
    "dataSource": "sbvrdev",
    "public": true
  },
  "project": {
    "dataSource": "sbvrdev",
    "public": true
  },
  "team": {
    "dataSource": "sbvrdev",
    "public": false
  },
  "document": {
    "dataSource": "sbvrdev",
    "public": true
  },
  "block": {
    "dataSource": "sbvrdev",
    "public": true
  },
  "section": {
    "dataSource": "sbvrdev",
    "public": true
  }
}
